{"GlobalPropertiesHash":"uFa+ihOoo4rCnWUUUOM6dRRp9C3yajpABtPZKFD++T8=","FingerprintPatternsHash":"gq3WsqcKBUGTSNle7RKKyXRIwh7M8ccEqOqYvIzoM04=","PropertyOverridesHash":"8ZRc1sGeVrPBx4lD717BgRaQekyh78QKV9SKsdt638U=","InputHashes":["JtKSkSJZlXwY/TiIyWZ4Wnv9k\u002Bfr8Riv1DwyLy267BE=","HuLW8dAICTvjNhk/YuocIkW018kL22zfvhxKrNIPcqU=","FKzUU7nF\u002B4iVjtYBOcnPRe8yqXb0V0Ns/URa/aIN14U=","cCe\u002BTgLVihCj7bo1gBGDmaDrfpgC264UpwApefBlmrQ=","8YTf9p6C6/LOwk/5HlsZ3IQ8rSyXqKT3mAxRU9wO24A=","aN/B443CjIK9xEJ1fGh2VzWj0KZMctKvFizv361cvek=","sKj0INQCNfWxfrheFs25IbilXNYZFK8HsCIiyOSDwOU=","uh6iWS/m2X5bDOEKJa/V6wouBOXFbCalHhjjU6dvnRY=","PozF1YVv8Oy8bijOqUQjv7rwXwkhSG7vAyhXIrn9k/8=","J5NtaQWFWACdmBHu0QWBSccdnXamOKDYxdLYuHEahuc=","1ma2d5AiTeA2Rc8gMVcsE9jcxYgWtc1j87lUwZmdBFU=","4y\u002BYmOVP0UHiDwjDAIeJoF4SvOQqlW/DypKHq5084hM=","4Eq\u002Bf3wOrPJPU8BYLD1y65M0lbvaKOMpd9m30HB/PBc="],"CachedAssets":{"FKzUU7nF\u002B4iVjtYBOcnPRe8yqXb0V0Ns/URa/aIN14U=":{"Identity":"D:\\Web\\MyMvcProject\\wwwroot\\css\\site.css","SourceId":"MyMvcProject","SourceType":"Discovered","ContentRoot":"D:\\Web\\MyMvcProject\\wwwroot\\","BasePath":"_content/MyMvcProject","RelativePath":"css/site#[.{fingerprint}]?.css","AssetKind":"All","AssetMode":"All","AssetRole":"Primary","AssetMergeBehavior":null,"AssetMergeSource":"","RelatedAsset":null,"AssetTraitName":null,"AssetTraitValue":null,"Fingerprint":"15dsdrvf0w","Integrity":"hVr5t03V4MYLs4HyoNzaOrl0xyqtyUF3\u002BpY3uclR9h4=","CopyToOutputDirectory":"Never","CopyToPublishDirectory":"PreserveNewest","OriginalItemSpec":"wwwroot\\css\\site.css","FileLength":220,"LastWriteTime":"2026-04-20T11:37:46.3075176+00:00"},"J5NtaQWFWACdmBHu0QWBSccdnXamOKDYxdLYuHEahuc=":{"Identity":"D:\\Web\\MyMvcProject\\wwwroot\\js\\site.js","SourceId":"MyMvcProject","SourceType":"Discovered","ContentRoot":"D:\\Web\\MyMvcProject\\wwwroot\\","BasePath":"_content/MyMvcProject","RelativePath":"js/site#[.{fingerprint}]?.js","AssetKind":"All","AssetMode":"All","AssetRole":"Primary","AssetMergeBehavior":null,"AssetMergeSource":"","RelatedAsset":null,"AssetTraitName":null,"AssetTraitValue":null,"Fingerprint":"uzehl5cx1q","Integrity":"1jAgQvbzyATcb8\u002BDpJ9QSCTj6k4PozAIo5DJgN2/yms=","CopyToOutputDirectory":"Never","CopyToPublishDirectory":"PreserveNewest","OriginalItemSpec":"wwwroot\\js\\site.js","FileLength":68,"LastWriteTime":"2026-04-20T11:37:48.322912+00:00"},"sKj0INQCNfWxfrheFs25IbilXNYZFK8HsCIiyOSDwOU=":{"Identity":"D:\\Web\\MyMvcProject\\wwwroot\\js\\cards.js","SourceId":"MyMvcProject","SourceType":"Discovered","ContentRoot":"D:\\Web\\MyMvcProject\\wwwroot\\","BasePath":"_content/MyMvcProject","RelativePath":"js/cards#[.{fingerprint}]?.js","AssetKind":"All","AssetMode":"All","AssetRole":"Primary","AssetMergeBehavior":null,"AssetMergeSource":"","RelatedAsset":null,"AssetTraitName":null,"AssetTraitValue":null,"Fingerprint":"mzgrcf122y","Integrity":"wkaszJh\u002BDqtHxn/EvY7UNqYSaikMRUuklwpWD8V7DqI=","CopyToOutputDirectory":"Never","CopyToPublishDirectory":"PreserveNewest","OriginalItemSpec":"wwwroot\\js\\cards.js","FileLength":10977,"LastWriteTime":"2026-04-21T14:18:37.941187+00:00"},"1ma2d5AiTeA2Rc8gMVcsE9jcxYgWtc1j87lUwZmdBFU=":{"Identity":"D:\\Web\\MyMvcProject\\wwwroot\\js\\sound.js","SourceId":"MyMvcProject","SourceType":"Discovered","ContentRoot":"D:\\Web\\MyMvcProject\\wwwroot\\","BasePath":"_content/MyMvcProject","RelativePath":"js/sound#[.{fingerprint}]?.js","AssetKind":"All","AssetMode":"All","AssetRole":"Primary","AssetMergeBehavior":null,"AssetMergeSource":"","RelatedAsset":null,"AssetTraitName":null,"AssetTraitValue":null,"Fingerprint":"hy6jiwg5ga","Integrity":"B0RQF09Fno3EX9/O8QmGtrR62i7dNxIPe4qPJUdQ6Ts=","CopyToOutputDirectory":"Never","CopyToPublishDirectory":"PreserveNewest","OriginalItemSpec":"wwwroot\\js\\sound.js","FileLength":11188,"LastWriteTime":"2026-04-21T12:20:08.336575+00:00"},"aN/B443CjIK9xEJ1fGh2VzWj0KZMctKvFizv361cvek=":{"Identity":"D:\\Web\\MyMvcProject\\wwwroot\\js\\admin.js","SourceId":"MyMvcProject","SourceType":"Discovered","ContentRoot":"D:\\Web\\MyMvcProject\\wwwroot\\","BasePath":"_content/MyMvcProject","RelativePath":"js/admin#[.{fingerprint}]?.js","AssetKind":"All","AssetMode":"All","AssetRole":"Primary","AssetMergeBehavior":null,"AssetMergeSource":"","RelatedAsset":null,"AssetTraitName":null,"AssetTraitValue":null,"Fingerprint":"e23gkgabgl","Integrity":"eliyRX1LOzSz7iOoIdBgl4a2TAx\u002BHO/2UQ0UuZ0krqg=","CopyToOutputDirectory":"Never","CopyToPublishDirectory":"PreserveNewest","OriginalItemSpec":"wwwroot\\js\\admin.js","FileLength":17025,"LastWriteTime":"2026-04-21T12:10:27.2879339+00:00"},"8YTf9p6C6/LOwk/5HlsZ3IQ8rSyXqKT3mAxRU9wO24A=":{"Identity":"D:\\Web\\MyMvcProject\\wwwroot\\index.html","SourceId":"MyMvcProject","SourceType":"Discovered","ContentRoot":"D:\\Web\\MyMvcProject\\wwwroot\\","BasePath":"_content/MyMvcProject","RelativePath":"index#[.{fingerprint}]?.html","AssetKind":"All","AssetMode":"All","AssetRole":"Primary","AssetMergeBehavior":null,"AssetMergeSource":"","RelatedAsset":null,"AssetTraitName":null,"AssetTraitValue":null,"Fingerprint":"8ka8v0rxhr","Integrity":"iKmVBYz/tAjWrGqucte430It/\u002Bsg9ng67a8Z5XYTCkY=","CopyToOutputDirectory":"Never","CopyToPublishDirectory":"PreserveNewest","OriginalItemSpec":"wwwroot\\index.html","FileLength":6523,"LastWriteTime":"2026-04-22T06:09:53.0298998+00:00"},"uh6iWS/m2X5bDOEKJa/V6wouBOXFbCalHhjjU6dvnRY=":{"Identity":"D:\\Web\\MyMvcProject\\wwwroot\\js\\gacha.js","SourceId":"MyMvcProject","SourceType":"Discovered","ContentRoot":"D:\\Web\\MyMvcProject\\wwwroot\\","BasePath":"_content/MyMvcProject","RelativePath":"js/gacha#[.{fingerprint}]?.js","AssetKind":"All","AssetMode":"All","AssetRole":"Primary","AssetMergeBehavior":null,"AssetMergeSource":"","RelatedAsset":null,"AssetTraitName":null,"AssetTraitValue":null,"Fingerprint":"d9s1m6rdey","Integrity":"rxylDS\u002Bi/ozVSUdv9gMRAl/47sxM59WrQJfKrAzvM7Q=","CopyToOutputDirectory":"Never","CopyToPublishDirectory":"PreserveNewest","OriginalItemSpec":"wwwroot\\js\\gacha.js","FileLength":6486,"LastWriteTime":"2026-04-21T14:18:30.8582939+00:00"},"HuLW8dAICTvjNhk/YuocIkW018kL22zfvhxKrNIPcqU=":{"Identity":"D:\\Web\\MyMvcProject\\wwwroot\\css\\game.css","SourceId":"MyMvcProject","SourceType":"Discovered","ContentRoot":"D:\\Web\\MyMvcProject\\wwwroot\\","BasePath":"_content/MyMvcProject","RelativePath":"css/game#[.{fingerprint}]?.css","AssetKind":"All","AssetMode":"All","AssetRole":"Primary","AssetMergeBehavior":null,"AssetMergeSource":"","RelatedAsset":null,"AssetTraitName":null,"AssetTraitValue":null,"Fingerprint":"o86ocx4gwt","Integrity":"aNrnU9huCqS2TwdTkFdjSPpeECO12m1gRpaS1wsyj9M=","CopyToOutputDirectory":"Never","CopyToPublishDirectory":"PreserveNewest","OriginalItemSpec":"wwwroot\\css\\game.css","FileLength":8064,"LastWriteTime":"2026-04-21T12:35:23.289948+00:00"},"cCe\u002BTgLVihCj7bo1gBGDmaDrfpgC264UpwApefBlmrQ=":{"Identity":"D:\\Web\\MyMvcProject\\wwwroot\\gacha.html","SourceId":"MyMvcProject","SourceType":"Discovered","ContentRoot":"D:\\Web\\MyMvcProject\\wwwroot\\","BasePath":"_content/MyMvcProject","RelativePath":"gacha#[.{fingerprint}]?.html","AssetKind":"All","AssetMode":"All","AssetRole":"Primary","AssetMergeBehavior":null,"AssetMergeSource":"","RelatedAsset":null,"AssetTraitName":null,"AssetTraitValue":null,"Fingerprint":"58vxywl8bu","Integrity":"q7Fa8caYhimR/dh4Or2FYbj7b7eCS6pFPPkhLs\u002BX69s=","CopyToOutputDirectory":"Never","CopyToPublishDirectory":"PreserveNewest","OriginalItemSpec":"wwwroot\\gacha.html","FileLength":7136,"LastWriteTime":"2026-04-21T12:35:23.2893641+00:00"},"JtKSkSJZlXwY/TiIyWZ4Wnv9k\u002Bfr8Riv1DwyLy267BE=":{"Identity":"D:\\Web\\MyMvcProject\\wwwroot\\cards.html","SourceId":"MyMvcProject","SourceType":"Discovered","ContentRoot":"D:\\Web\\MyMvcProject\\wwwroot\\","BasePath":"_content/MyMvcProject","RelativePath":"cards#[.{fingerprint}]?.html","AssetKind":"All","AssetMode":"All","AssetRole":"Primary","AssetMergeBehavior":null,"AssetMergeSource":"","RelatedAsset":null,"AssetTraitName":null,"AssetTraitValue":null,"Fingerprint":"qpob860c1a","Integrity":"Is6W4sYD5SGozb6BFTaz3y9cCWEyXHE8ZSMXBpqXkWw=","CopyToOutputDirectory":"Never","CopyToPublishDirectory":"PreserveNewest","OriginalItemSpec":"wwwroot\\cards.html","FileLength":3477,"LastWriteTime":"2026-04-21T12:35:23.2893641+00:00"},"PozF1YVv8Oy8bijOqUQjv7rwXwkhSG7vAyhXIrn9k/8=":{"Identity":"D:\\Web\\MyMvcProject\\wwwroot\\js\\mystery-cards.js","SourceId":"MyMvcProject","SourceType":"Discovered","ContentRoot":"D:\\Web\\MyMvcProject\\wwwroot\\","BasePath":"_content/MyMvcProject","RelativePath":"js/mystery-cards#[.{fingerprint}]?.js","AssetKind":"All","AssetMode":"All","AssetRole":"Primary","AssetMergeBehavior":null,"AssetMergeSource":"","RelatedAsset":null,"AssetTraitName":null,"AssetTraitValue":null,"Fingerprint":"3pi93574e2","Integrity":"503xfRJd0RxDy4wONiLSd4U/iGo4EKgnyvxEblLAik4=","CopyToOutputDirectory":"Never","CopyToPublishDirectory":"PreserveNewest","OriginalItemSpec":"wwwroot\\js\\mystery-cards.js","FileLength":7783,"LastWriteTime":"2026-04-22T06:22:39.4057725+00:00"},"4y\u002BYmOVP0UHiDwjDAIeJoF4SvOQqlW/DypKHq5084hM=":{"Identity":"D:\\Web\\MyMvcProject\\wwwroot\\mystery-cards.html","SourceId":"MyMvcProject","SourceType":"Discovered","ContentRoot":"D:\\Web\\MyMvcProject\\wwwroot\\","BasePath":"_content/MyMvcProject","RelativePath":"mystery-cards#[.{fingerprint}]?.html","AssetKind":"All","AssetMode":"All","AssetRole":"Primary","AssetMergeBehavior":null,"AssetMergeSource":"","RelatedAsset":null,"AssetTraitName":null,"AssetTraitValue":null,"Fingerprint":"arksuq9l5p","Integrity":"6lEKACQJS8/UUTt6IuAdba5Tfyk9KFzEX\u002BTr562Na3I=","CopyToOutputDirectory":"Never","CopyToPublishDirectory":"PreserveNewest","OriginalItemSpec":"wwwroot\\mystery-cards.html","FileLength":4614,"LastWriteTime":"2026-04-22T06:21:43.8829222+00:00"}},"CachedCopyCandidates":{}}